{"corey_PUFTB_multiplier": 1, "corey_PUFTB_risk": 100, "corey_MNQ_multiplier": 1, "corey_MNQ_risk": 232, "corey_QTSTT_multiplier": 1, "corey_QTSTT_risk": 100, "corey_STSTT_multiplier": 1, "corey_STSTT_risk": 100, "corey_IWTSTT_multiplier": 1, "corey_IWTSTT_risk": 100, "corey_OTS_multiplier": 1, "corey_OTS_risk": 100, "corey_STS_multiplier": 1, "corey_STS_risk": 100, "corey_YBO_multiplier": 1, "corey_YBO_risk": 100, "corey_QCK_multiplier": 1, "corey_QCK_risk": 100, "corey_TEST_multiplier": 1, "corey_TEST_risk": 100}